dashai_img_mlp_plugin2/__init__.py
dashai_img_mlp_plugin2/dataloader_class_template.py
dashai_img_mlp_plugin2/metric_class_template.py
dashai_img_mlp_plugin2/model_class_template.py
dashai_img_mlp_plugin2/task_class_template.py
dashai_img_mlp_plugin2-0.0.2.dist-info/METADATA
dashai_img_mlp_plugin2-0.0.2.dist-info/WHEEL
dashai_img_mlp_plugin2-0.0.2.dist-info/entry_points.txt
dashai_img_mlp_plugin2-0.0.2.dist-info/RECORD
