Metadata-Version: 2.3
Name: dashai_img_mlp_plugin2
Version: 0.0.2
Summary: DashAI Plugin description
Author: francisca
Author-email: francisca.cona@ug.uchile.cl
Keywords: DashAI,Dataloader,Metric,Model,Task
Requires-Python: >=3.8
